README.md
setup.py
simpdatasets/__init__.py
simpdatasets/dataset.py
simpdatasets.egg-info/PKG-INFO
simpdatasets.egg-info/SOURCES.txt
simpdatasets.egg-info/dependency_links.txt
simpdatasets.egg-info/top_level.txt