Metadata-Version: 2.1
Name: simpdatasets
Version: 0.1.0
Summary: Simple Data Set Structure
Home-page: https://github.com/StephenMal/SimpDataSets
Author: Stephen Maldonado
Author-email: simpdatasets@stephenmal.com
License: UNKNOWN
Platform: UNKNOWN
Classifier: Development Status :: 1 - Planning
Classifier: Programming Language :: Python :: 3 :: Only
Classifier: Topic :: Utilities
